{
  "Edit": "Edit",
  "Name": "",
  "PROFILE PAGE": "PROFILE PAGE",
  "Profile": "Profile",
  "Surname": "",
  "about": "",
  "about page": "",
  "authorisation form": "",
  "authorization form": "authorization form",
  "blabla": "",
  "decrement": "decrement",
  "incorrect login or password": "",
  "increment": "increment",
  "language": "",
  "main": "",
  "name": "name",
  "no page": "no page",
  "password": "password",
  "sign in": "sign in",
  "sign out": "sign out",
  "sing in": "sing in",
  "surname": "surname",
  "throw error": "throw error",
  "toggle": "toggle",
  "toglle": "toglle",
  "user name": "user name",
  "Обновить страницу": "Обновить страницу",
  "Переключить": "",
  "Произошла непредвиденная ошибка": "Произошла непредвиденная ошибка"
}
